dcc/__init__.py
dcc/__main__.py
dcc/_version.py
dcc/env.py
dcc/exceptions.py
dcc/parsers.py
dcc/records.py
dcc/sessions.py
dcc/testing.py
dcc/util.py
dcc-0.8.0.dist-info/LICENSE
dcc-0.8.0.dist-info/METADATA
dcc-0.8.0.dist-info/WHEEL
dcc-0.8.0.dist-info/entry_points.txt
dcc-0.8.0.dist-info/top_level.txt
dcc-0.8.0.dist-info/RECORD
