Metadata-Version: 2.1
Name: dcc
Version: 0.8.0
Summary: Tools for interactive and programmatic access to the LIGO DCC.
Home-page: https://docs.ligo.org/sean-leavey/dcc/
Author: Sean Leavey
Author-email: sean.leavey@ligo.org
License: GPL-3.0-or-later
Download-URL: https://docs.ligo.org/sean-leavey/dcc/installation.html
Project-URL: Bug Tracker, https://git.ligo.org/sean-leavey/dcc/-/issues
Project-URL: Source Code, https://git.ligo.org/sean-leavey/dcc/
Project-URL: Documentation, https://docs.ligo.org/sean-leavey/dcc/
Platform: UNKNOWN
Classifier: Development Status :: 4 - Beta
Classifier: Intended Audience :: Science/Research
Classifier: License :: OSI Approved :: GNU General Public License v3 or later (GPLv3+)
Classifier: Natural Language :: English
Classifier: Operating System :: OS Independent
Classifier: Programming Language :: Python
Classifier: Programming Language :: Python :: 3
Classifier: Programming Language :: Python :: 3.8
Classifier: Programming Language :: Python :: 3.9
Classifier: Programming Language :: Python :: 3.10
Classifier: Topic :: Scientific/Engineering :: Astronomy
Classifier: Topic :: Scientific/Engineering :: Physics
Requires-Python: >=3.8
Provides-Extra: dev
License-File: LICENSE
